SpringSession212ReleaseZhongwenWendang/README.md
SpringSession212ReleaseZhongwenWendang/__init__.py
SpringSession212ReleaseZhongwenWendang/__main__.py
SpringSession212ReleaseZhongwenWendang/file.epub
SpringSession212ReleaseZhongwenWendang/index.html
SpringSession212ReleaseZhongwenWendang/css/__init__.py
SpringSession212ReleaseZhongwenWendang/css/annotations.css
SpringSession212ReleaseZhongwenWendang/css/main.css
SpringSession212ReleaseZhongwenWendang/css/normalize.css
SpringSession212ReleaseZhongwenWendang/css/popup.css
SpringSession212ReleaseZhongwenWendang/font/__init__.py
SpringSession212ReleaseZhongwenWendang/font/fontello.eot
SpringSession212ReleaseZhongwenWendang/font/fontello.svg
SpringSession212ReleaseZhongwenWendang/font/fontello.ttf
SpringSession212ReleaseZhongwenWendang/font/fontello.woff
SpringSession212ReleaseZhongwenWendang/img/__init__.py
SpringSession212ReleaseZhongwenWendang/img/annotator-glyph-sprite.png
SpringSession212ReleaseZhongwenWendang/img/annotator-icon-sprite.png
SpringSession212ReleaseZhongwenWendang/img/apple-touch-icon.png
SpringSession212ReleaseZhongwenWendang/img/cancelfullscreen.png
SpringSession212ReleaseZhongwenWendang/img/close.png
SpringSession212ReleaseZhongwenWendang/img/fullscreen.png
SpringSession212ReleaseZhongwenWendang/img/loader.gif
SpringSession212ReleaseZhongwenWendang/img/menu-icon.png
SpringSession212ReleaseZhongwenWendang/img/save.png
SpringSession212ReleaseZhongwenWendang/img/saved.png
SpringSession212ReleaseZhongwenWendang/img/settings-s.png
SpringSession212ReleaseZhongwenWendang/img/settings.png
SpringSession212ReleaseZhongwenWendang/img/star.png
SpringSession212ReleaseZhongwenWendang/js/__init__.py
SpringSession212ReleaseZhongwenWendang/js/epub.js
SpringSession212ReleaseZhongwenWendang/js/epub.min.js
SpringSession212ReleaseZhongwenWendang/js/epub.min.map
SpringSession212ReleaseZhongwenWendang/js/hooks.min.js
SpringSession212ReleaseZhongwenWendang/js/hooks.min.map
spring_session_2_1_2_release_zhongwen_wendang-2024.3.5.0.dist-info/METADATA
spring_session_2_1_2_release_zhongwen_wendang-2024.3.5.0.dist-info/WHEEL
spring_session_2_1_2_release_zhongwen_wendang-2024.3.5.0.dist-info/entry_points.txt
spring_session_2_1_2_release_zhongwen_wendang-2024.3.5.0.dist-info/top_level.txt
spring_session_2_1_2_release_zhongwen_wendang-2024.3.5.0.dist-info/RECORD
